BBGHL/__init__.py
BBGHL/ghlFunctions.py
BigBrainGHLPy-0.0.11.dist-info/LICENSE
BigBrainGHLPy-0.0.11.dist-info/METADATA
BigBrainGHLPy-0.0.11.dist-info/WHEEL
BigBrainGHLPy-0.0.11.dist-info/top_level.txt
BigBrainGHLPy-0.0.11.dist-info/RECORD
