Metadata-Version: 2.1
Name: BigBrainGHLPy
Version: 0.0.11
Summary: A basic python wrapper for GoHighLevel
Author: xtrakTD
Author-email: <dmitry.m@bbdmgroup.com>
Keywords: python,ghl,gohighlevel,api,wrapper
Classifier: Development Status :: 1 - Planning
Classifier: Intended Audience :: Developers
Classifier: Programming Language :: Python :: 3
Classifier: Operating System :: Unix
Classifier: Operating System :: MacOS :: MacOS X
Classifier: Operating System :: Microsoft :: Windows
License-File: LICENSE
Requires-Dist: GHLPy
